moat/link/__init__.py
moat/link/_cfg.yaml
moat/link/_data.py
moat/link/_main.py
moat/link/_test.py
moat/link/announce.py
moat/link/auth.py
moat/link/client.py
moat/link/common.py
moat/link/conn.py
moat/link/exceptions.py
moat/link/hello.py
moat/link/host.py
moat/link/meta.py
moat/link/schema.py
moat/link/backend/__init__.py
moat/link/backend/mqtt.py
moat/link/cmd/__init__.py
moat/link/cmd/cmd.py
moat/link/cmd/data.py
moat/link/cmd/error.py
moat/link/cmd/host.py
moat/link/cmd/raw.py
moat/link/node/__init__.py
moat/link/node/codec.py
moat_link-0.2.46.dist-info/licenses/LICENSE.txt
moat_link-0.2.46.dist-info/METADATA
moat_link-0.2.46.dist-info/WHEEL
moat_link-0.2.46.dist-info/top_level.txt
moat_link-0.2.46.dist-info/RECORD
