Metadata-Version: 2.4
Name: moat-link
Version: 0.2.46
Summary: Message exchange between MoaT instances
Author-email: Matthias Urlichs <matthias@urlichs.de>
Project-URL: homepage, https://m-o-a-t.org
Project-URL: repository, https://github.com/M-o-a-T/moat
Keywords: MoaT
Classifier: Intended Audience :: Developers
Classifier: Programming Language :: Python :: 3
Classifier: Framework :: AsyncIO
Classifier: Framework :: Trio
Classifier: Framework :: AnyIO
Classifier: Development Status :: 4 - Beta
Requires-Python: >=3.8
License-File: LICENSE.txt
Requires-Dist: anyio~=4.2
Requires-Dist: asyncclick
Requires-Dist: attrs
Requires-Dist: msgpack
Requires-Dist: outcome
Requires-Dist: ruyaml
Requires-Dist: httpx
Requires-Dist: simpleeval
Requires-Dist: transitions_aio~=0.9.3.4
Requires-Dist: moat-util~=0.62.2
Requires-Dist: moat-lib-rpc~=0.5.1
Requires-Dist: moat-lib-priomap~=0.2.3
Requires-Dist: moat-lib-mqtt~=0.0.1
Requires-Dist: moat-lib-codec~=0.4.10
Requires-Dist: moat-lib-config~=0.1.1
Requires-Dist: moat-lib-proxy~=0.1.0
Requires-Dist: moat-lib-run~=0.1.1
Requires-Dist: moat-link-server~=0.3.25
Requires-Dist: moat-lib-broadcast~=0.1.2
Dynamic: license-file
